SKPython/__init__.py
SKPython/crypto.py
SKPython/graceful_shutdown.py
SKPython/mongodb.py
SKPython/mysql.py
SKPython/object_mapper.py
SKPython/rabbitmq.py
SKPython/redis.py
SKPython/redis_async.py
SKPython/slack.py
SKPython-0.0.38.dist-info/METADATA
SKPython-0.0.38.dist-info/WHEEL
SKPython-0.0.38.dist-info/top_level.txt
SKPython-0.0.38.dist-info/RECORD
