Metadata-Version: 2.1
Name: SKPython
Version: 0.0.38
Summary: Python 편의용
Home-page: 
Author: kaldron27
Author-email: kaldron27@gmail.com
License: MIT
Requires-Python: >=3
Requires-Dist: redis >=4.4.0
Requires-Dist: mysql-connector-python >=8.0.29
Requires-Dist: dacite >=1.6.0
Requires-Dist: requests >=2.28.1
Requires-Dist: pycryptodome >=3.15.0
